avenieca/__init__.py
avenieca/consumer.py
avenieca/data.py
avenieca/producer.py
avenieca/api/__init__.py
avenieca/api/auth.py
avenieca/api/client.py
avenieca/api/cortex.py
avenieca/api/document.py
avenieca/api/eca.py
avenieca/api/ecaresponse.py
avenieca/api/embedding.py
avenieca/api/ess.py
avenieca/api/model.py
avenieca/api/retrieval.py
avenieca/api/sequence.py
avenieca/api/utils/__init__.py
avenieca/api/utils/response.py
avenieca/config/__init__.py
avenieca/config/broker.py
avenieca/config/cortex.py
avenieca/config/db.py
avenieca/config/document.py
avenieca/config/embedding.py
avenieca/config/log.py
avenieca/config/ras.py
avenieca/config/retrieval.py
avenieca/config/server.py
avenieca/config/twin.py
avenieca/config/vse.py
avenieca/producers/__init__.py
avenieca/producers/event.py
avenieca/producers/stream.py
avenieca/utils/__init__.py
avenieca/utils/hash.py
avenieca/utils/signal.py
avenieca_python-0.1.4.dist-info/LICENSE
avenieca_python-0.1.4.dist-info/METADATA
avenieca_python-0.1.4.dist-info/WHEEL
avenieca_python-0.1.4.dist-info/top_level.txt
avenieca_python-0.1.4.dist-info/RECORD
