Metadata-Version: 2.1
Name: avenieca-python
Version: 0.1.4
Summary: Python SDK for AveniECA
Home-page: https://github.com/aveni-hub/avenieca-python
Author: Ogban Ugot
Author-email: ogbanugot@gmail.com
License: MIT
Classifier: License :: OSI Approved :: GNU General Public License v3 (GPLv3)
Classifier: Programming Language :: Python
Classifier: Programming Language :: Python :: 3
License-File: LICENSE
Requires-Dist: kafka-python
Requires-Dist: numpy
Requires-Dist: requests
Requires-Dist: dataclass-wizard
